furs_fiscalization/__init__.py
furs_fiscalization/api.py
furs_fiscalization/base_api.py
furs_fiscalization/connector.py
furs_fiscalization/exceptions.py
furs_fiscalization/logging_utils.py
furs_fiscalization-1.0.14.dist-info/licenses/LICENSE
furs_fiscalization-1.0.14.dist-info/METADATA
furs_fiscalization-1.0.14.dist-info/WHEEL
furs_fiscalization-1.0.14.dist-info/top_level.txt
furs_fiscalization-1.0.14.dist-info/RECORD
